digReviewIDExtractor
test
