Metadata-Version: 1.1
Name: digReviewIDExtractor
Version: 0.2.0
Summary: digReviewIDExtractor
Home-page: https://github.com/usc-isi-i2/dig-review-id-extractor
Author: Lingzhe Teng
Author-email: zwein27@gmail.com
License: UNKNOWN
Download-URL: https://github.com/usc-isi-i2/dig-review-id-extractor
Keywords: review,id,extractor
Platform: UNKNOWN
